PhishingTracker/__init__.py
PhishingTracker/__name__.py
PhishingTracker/__version__.py
PhishingTracker/analyzers.py
PhishingTracker/certificate.py
PhishingTracker/dig.py
PhishingTracker/exceptions.py
PhishingTracker/file.py
PhishingTracker/logger.py
PhishingTracker/main.py
PhishingTracker/meta.py
PhishingTracker/safebrowsing.py
PhishingTracker/safebrowsing_client.py
PhishingTracker/smtp.py
PhishingTracker/tests.py
PhishingTracker/useragent.py
PhishingTracker/util.py
PhishingTracker/web.py
PhishingTracker/whois.py
phishing_tracker-0.0.7.data/scripts/phishing-tracker
tests/__init__.py
tests/test_analyzers.py
tests/test_basic.py
tests/test_examples.py
tests/test_trivial.py
phishing_tracker-0.0.7.dist-info/LICENSE
phishing_tracker-0.0.7.dist-info/METADATA
phishing_tracker-0.0.7.dist-info/WHEEL
phishing_tracker-0.0.7.dist-info/top_level.txt
phishing_tracker-0.0.7.dist-info/RECORD
