Metadata-Version: 2.1
Name: phishing-tracker
Version: 0.0.7
Summary: Utility to manage sets of phishing links making it easier to track their removal progress over time.
Home-page: https://github.com/ndejong/phishing-tracker
Author: Nicholas de Jong
Author-email: contact@nicholasdejong.com
License: BSD 2-Clause
Keywords: phish,phishing,url,cyber-crime
Platform: UNKNOWN
Classifier: Environment :: Console
Classifier: Intended Audience :: System Administrators
Classifier: Intended Audience :: Information Technology
Classifier: Programming Language :: Python :: 3
Classifier: Programming Language :: Python :: 3.6
Classifier: Programming Language :: Python :: 3.7
Classifier: Programming Language :: Python :: 3.8
Classifier: License :: OSI Approved :: BSD License
Requires-Dist: pydig
Requires-Dist: pyyaml
Requires-Dist: requests
Requires-Dist: eventlet
Requires-Dist: dateparser
Requires-Dist: tldextract
Requires-Dist: python-whois
